{
  "html": {
    "snippets": {
      "meta:x": "<meta http-equiv=\"x-ua-compatible\" content=\"ie=edge\">",
      "meta:v": "<meta name=\"viewport\" content=\"width=device-width, initial-scale=1.0\">",
      "meta:r": "<meta http-equiv=\"refresh\" content=\"30\">",
      "meta:t": "<meta name=\"theme\" content=\"${1}\" >",
      "meta:a": "<meta name=\"author\" content=\"${1}\" >",
      "meta:d": "<meta name=\"description\" content=\"${1}\" >",
      "meta:k": "<meta name=\"keywords\" content=\"${1}\" >",
      "img": "<img class=\"img\" src=\"${1}\" loading=\"lazy\" alt=\"img\"></img>",
      "label": "<label class=\"label\">${1}</label>",
      "toggler": "<span class=\"toggler\"><i class=\"bi bi-close-lg\"></i></span>",
      "form": "<form class=\"form\" method=\"POST\">\n\t<label class=\"label\">${1}</label>\n\t<input class=\"input\" type=\"text\" name=\"input\"></input>\n</form>",
      "input": "<input class=\"input\" name=\"input\" type=\"text\"></input>",
      "video": "<video class=\"video\" src=\"${1}\" loading=\"lazy\" alt=\"video\"></video>",
      "hero": "<div class=\"hero\"></div>",
      "btn": "<button class=\"btn\"></button>",
      "panel": "<div class=\"panel\">\n\t<div class=\"panel-wrapper\">${1}</div>\n</div>",
      "footer": "<div class=\"footer\">\n\t<div class=\"footer-wrapper\">${1}</div>\n</div>",
      "group": "<ul class=\"group\">\n\t<li class=\"group-item\">${1}</li>\n</ul>",
      "list": "<ul class=\"list\">\n\t<li class=\"list-item\">${1}</li>\n</ul>",
      "pagination": "<ul class=\"pagination\">\n\t<li class=\"pagination-item\">${1}</li>\n</ul>",
      "badge": "<div class=\"badge\">\n\t<div class=\"badge-wrapper\">${1}</div>\n</div>",
      "box": "<div class=\"box\">\n\t<div class=\"box-wrapper\">${1}</div>\n</div>",
      "preloader": "<div class=\"preloader\">${1}</div>",
      "msg": "<div class=\"msg\">\n\t<div class=\"msg-wrapper\">${1}</div>\n</div>",
      "notification": "<div class=\"notification\">\n\t<div class=\"notification-wrapper\">${1}</div>\n</div>",
      "alert": "<div class=\"alert\">\n\t<div class=\"alert-wrapper\">${1}</div>\n</div>",
      "progress": "<div class=\"progress\">\n\t<div class=\"progress-meter\">${1}</div>\n</div>",
      "scroll-tracker": "<div class=\"scroll-tracker\"></div>",
      "carousel": "<div class=\"carousel\">\n\t<div class=\"carousel-wrapper\">${1}</div>\n</div>",
      "dropdown": "<div class=\"dropdown\">\n\t<div class=\"dropdown-wrapper\">${1}</div>\n</div>",
      "modal": "<div class=\"modal\">\n\t<div class=\"modal-wrapper\">${1}</div>\n</div>",
      "tooltip": "<div class=\"tooltip\">\n\t<span class=\"tooltip-text\">${1}</span>\n</div>",
      "sidebar": "<div class=\"sidebar\">\n\t<div class=\"sidebar-wrapper\">${1}</div>\n</div>",
      "table": "<table class=\"table responsive\">\n\t<tr class=\"tr\">\n\t\t<td class=\"td\">${1}</td>\n</tr>\n</table>",
      "hamberger": "<div class=\"hamberger\">\n\t<div class=\"hamberger-bar\">${1}</div>\n\t<div class=\"hamberger-bar hamberger-bar-short\">${1}</div>\n\t<div class=\"hamberger-bar\">${1}</div>\n</div>",
      "notepad": "<div class=\"notepad\">\n\t<h3 class=\"notepad-title\">${1}</h3>\n</div>"
    }
  },
  "css": {
    "snippets": {
      "cb": "color: black",
      "bsd": "border: 1px solid ${1:red}",
      "ls": "list-style: ${1}"
    }
  }
}
